a4x_pegasus_wms/__init__.py
a4x_pegasus_wms/version.py
a4x_pegasus_wms-0.1.0a1.dist-info/licenses/LICENSE.md
a4x_pegasus_wms-0.1.0a1.dist-info/METADATA
a4x_pegasus_wms-0.1.0a1.dist-info/WHEEL
a4x_pegasus_wms-0.1.0a1.dist-info/entry_points.txt
a4x_pegasus_wms-0.1.0a1.dist-info/top_level.txt
a4x_pegasus_wms-0.1.0a1.dist-info/RECORD
