Metadata-Version: 2.4
Name: a4x-pegasus-wms
Version: 0.1.0a1
Summary: Pegasus WMS plugin for the A4X Orchestrator
Author-email: Rajiv Mayani <mayani@isi.edu>
Maintainer-email: Rajiv Mayani <mayani@isi.edu>
License-Expression: Apache-2.0
Project-URL: Homepage, https://pegasus.isi.edu
Project-URL: Repository, https://github.com/pegasus-isi/a4x-pegasus-wms.git
Project-URL: Issues, https://github.com/pegasus-isi/a4x-pegasus-wms/issues
Project-URL: Changelog, https://github.com/pegasus-isi/a4x-pegasus-wms/blob/master/CHANGELOG.md
Project-URL: Documentation, https://a4x-pegasus-wms.readthedocs.io/en/latest/
Classifier: Development Status :: 1 - Planning
Classifier: Programming Language :: Python
Classifier: Programming Language :: Python :: 3
Classifier: Programming Language :: Python :: 3.7
Classifier: Programming Language :: Python :: 3.8
Classifier: Programming Language :: Python :: 3.9
Classifier: Programming Language :: Python :: 3.10
Classifier: Programming Language :: Python :: 3.11
Classifier: Programming Language :: Python :: 3.12
Classifier: Programming Language :: Python :: 3.13
Classifier: Operating System :: Unix
Classifier: Operating System :: MacOS
Classifier: Intended Audience :: Science/Research
Classifier: Topic :: Scientific/Engineering
Requires-Python: >=3.7
License-File: LICENSE.md
Requires-Dist: pegasus-wms.api
Requires-Dist: a4x-orchestration
Dynamic: license-file
